.project
.pydevproject
CHANGES.txt
README.txt
ez_setup.py
setup.cfg
setup.py
.settings/org.eclipse.core.resources.prefs
qubic/__init__.py
qubic.sphinx.graphvizinclude.egg-info/PKG-INFO
qubic.sphinx.graphvizinclude.egg-info/SOURCES.txt
qubic.sphinx.graphvizinclude.egg-info/dependency_links.txt
qubic.sphinx.graphvizinclude.egg-info/namespace_packages.txt
qubic.sphinx.graphvizinclude.egg-info/not-zip-safe
qubic.sphinx.graphvizinclude.egg-info/requires.txt
qubic.sphinx.graphvizinclude.egg-info/top_level.txt
qubic/sphinx/__init__.py
qubic/sphinx/graphvizinclude.py