Metadata-Version: 1.0
Name: qubic.sphinx.graphvizinclude
Version: 0.1
Summary: Sphinx extension: graphviz generation of external dot files
Home-page: UNKNOWN
Author: Nicolas Laurance
Author-email: nicolas[dot]laurance<at>gmail
License: MIT GPLv3
Keywords: sphinx graphviz
Platform: UNKNOWN
Classifier: Development Status :: 5 - Production/Stable
Classifier: Intended Audience :: Developers
Classifier: Programming Language :: Python
Classifier: Topic :: Documentation
